Workbook

Sheet DCF
B1: DCF valuation model - GENTEX - by Michael (Minh) Thai
B3: Ticker | C3: GNTX | E3: Implied Share Price | H3: =N119 -> 3.528661 | K3: Please choose the scenario from the "colored box" below
B4: Date | C4: 45799 | E4: Current Share Price | H4: 23.4 | J4: Scenario: | K4: Conservative | L4: {=_xlfn.IFS(K4="Conservative", 1, K4="Bear", 2, K4="Optimistic", 3, TRUE, 1)} -> 1
B5: Year-End | C5: 46022 | E5: Implied Upside / (Downside) | H5: =H3/H4-1 -> -0.84920252
A7: x | B7: Assumptions
B9: Switches | G9: Conservative | M9: Base | S9: Optimistic
B10: Revenue | G10: Revenue | J10: Year | K10: Metric | M10: Revenue | P10: Year | Q10: Metric | S10: Revenue | V10: Year | W10: Metric
B12: Insurance and Other | E12: =$L$4 -> 1 | G12: Revenue | J12: 2026 | K12: -0.073 | M12: Revenue | P12: 2026 | Q12: 0.046 | S12: Revenue | V12: 2026 | W12: 0.065
G13: Revenue | J13: 2030 | K13: 0.02 | M13: Revenue | P13: 2030 | Q13: 0.035 | S13: Revenue | V13: 2030 | W13: 0.065
B15: Costs & OpEx | G15: Costs & OpEx | J15: Year | K15: Metric | M15: Costs & OpEx | P15: Year | Q15: Metric | S15: Costs & OpEx | V15: Year | W15: Metric
B16: COGS | E16: =$L$4 -> 1 | G16: COGS | J16: 2026 | K16: 0.685 | M16: COGS | P16: 2026 | Q16: 0.655 | S16: COGS | V16: 2026 | W16: 0.65
B17: R&D Ex | E17: =$L$4 -> 1 | G17: COGS | J17: 2030 | K17: 0.68 | M17: COGS | P17: 2030 | Q17: 0.645 | S17: COGS | V17: 2030 | W17: 0.64
B18: SG&A | E18: =$L$4 -> 1 | G18: R&D Ex | J18: 2026 | K18: 0.086 | M18: R&D Ex | P18: 2026 | Q18: 0.08 | S18: R&D Ex | V18: 2026 | W18: 0.078
G19: R&D Ex | J19: 2030 | K19: 0.09 | M19: R&D Ex | P19: 2030 | Q19: 0.08 | S19: R&D Ex | V19: 2030 | W19: 0.075
G20: SG&A | J20: 2026 | K20: 0.084 | M20: SG&A | P20: 2026 | Q20: 0.076 | S20: SG&A | V20: 2026 | W20: 0.074
G21: SG&A | J21: 2030 | K21: 0.075 | M21: SG&A | P21: 2030 | Q21: 0.065 | S21: SG&A | V21: 2030 | W21: 0.055
B23: Valuation | G23: Valuation | K23: Metric | M23: Valuation | Q23: Metric | S23: Valuation | W23: Metric
B24: WACC | E24: =$L$4 -> 1 | G24: WACC | K24: 0.105 | M24: WACC | Q24: 0.095 | S24: WACC | W24: 0.085
B25: TGR | E25: =$L$4 -> 1 | G25: TGR | K25: 0.02 | M25: TGR | Q25: 0.03 | S25: TGR | W25: 0.04
B27: Other Assumptions
B28: Taxes | E28: 0.21
B29: D&A | E29: =AVERAGE(G76:I76) -> 0.040861849
B30: CapEx | E30: =AVERAGE(G79:I79) -> 0.064454107
B31: Change in NWC | E31: =AVERAGE(F82:I82) -> 0.012186713
B32: WACC | E32: =CHOOSE(E24,K24,Q24,W24) -> 0.105
B33: TGR | E33: =CHOOSE(E25,K25,Q25,W25) -> 0.02
A35: x | B35: Revenue Build | E35: 2021 | F35: =E35+1 -> 2022 | G35: =F35+1 -> 2023 | H35: =G35+1 -> 2024 | I35: =H35+1 -> 2025 | J35: =I35+1 -> 2026 | K35: =J35+1 -> 2027 | L35: =K35+1 -> 2028 | M35: =L35+1 -> 2029 | N35: =M35+1 -> 2030
B36: Revenue | E36: ='Income - As Reported'!C9 -> 1731.1699 | F36: ='Income - As Reported'!D9 -> 1918.958 | G36: ='Income - As Reported'!E9 -> 2299.215 | H36: ='Income - As Reported'!F9 -> 2313.3143 | I36: ='Income - As Reported'!G9 -> 2534.269 | J36: =I36*(1+J37) -> 2642.3353 | K36: =J36*(1+K37) -> 2747.7433 | L36: =K36*(1+L37) -> 2849.8 | M36: =L36*(1+M37) -> 2947.8103 | N36: =M36*(1+N37) -> 3006.7666
B37: % growth | E37: -- | F37: =F36/E36-1 -> 0.10847468 | G37: =G36/F36-1 -> 0.19815806 | H37: =H36/G36-1 -> 0.0061322234 | I37: =I36/H36-1 -> 0.095514345 | J37: =OFFSET(J37,$E$12,0) -> 0.042642 | K37: =OFFSET(K37,$E$12,0) -> 0.039892 | L37: =OFFSET(L37,$E$12,0) -> 0.037142 | M37: =OFFSET(M37,$E$12,0) -> 0.034392 | N37: =OFFSET(N37,$E$12,0) -> 0.02
B38: Conservative | J38: =J39*(1+K12) -> 0.042642 | K38: =J38-(($J$39-$N$39)/($N$35-$J$35)) -> 0.039892 | L38: =K38-(($J$39-$N$39)/($N$35-$J$35)) -> 0.037142 | M38: =L38-(($J$39-$N$39)/($N$35-$J$35)) -> 0.034392 | N38: =K13 -> 0.02
B39: Base | J39: =Q12 -> 0.046 | K39: =J39-(($J$39-$N$39)/($N$35-$J$35)) -> 0.04325 | L39: =K39-(($J$39-$N$39)/($N$35-$J$35)) -> 0.0405 | M39: =L39-(($J$39-$N$39)/($N$35-$J$35)) -> 0.03775 | N39: =Q13 -> 0.035
B40: Optimistic | J40: =J39*(1+W12) -> 0.04899 | K40: =J40-(($J$39-$N$39)/($N$35-$J$35)) -> 0.04624 | L40: =K40-(($J$39-$N$39)/($N$35-$J$35)) -> 0.04349 | M40: =L40-(($J$39-$N$39)/($N$35-$J$35)) -> 0.04074 | N40: =W13 -> 0.065
B43: Costs & OpEx Build | E43: 2021 | F43: =E43+1 -> 2022 | G43: =F43+1 -> 2023 | H43: =G43+1 -> 2024 | I43: =H43+1 -> 2025 | J43: =I43+1 -> 2026 | K43: =J43+1 -> 2027 | L43: =K43+1 -> 2028 | M43: =L43+1 -> 2029 | N43: =M43+1 -> 2030
B44: COGS | E44: ='Income - As Reported'!C12 -> 1111.4621 | F44: ='Income - As Reported'!D12 -> 1309.1439 | G44: ='Income - As Reported'!E12 -> 1536.585 | H44: ='Income - As Reported'!F12 -> 1542.2241 | I44: ='Income - As Reported'!G12 -> 1667.56 | J44: =J45*J$36 -> 2916.2794 | K44: =K45*K$36 -> 2741.5781 | L44: =L45*L$36 -> 2541.5585 | M44: =M45*M$36 -> 2316.7394 | N44: =N45*N$36 -> 2044.6013
B45: % margin | E45: =E44/E$36 -> 0.64202947 | F45: =F44/F$36 -> 0.68221603 | G45: =G44/G$36 -> 0.66830853 | H45: =H44/H$36 -> 0.66667296 | I45: =I44/I$36 -> 0.65800434 | J45: =OFFSET(J45,$E$16,0) -> 1.103675 | K45: =OFFSET(K45,$E$16,0) -> 0.99775625 | L45: =OFFSET(L45,$E$16,0) -> 0.8918375 | M45: =OFFSET(M45,$E$16,0) -> 0.78591875 | N45: =OFFSET(N45,$E$16,0) -> 0.68
B46: Conservative | J46: =J47*(1+K16) -> 1.103675 | K46: =J46-(($J$46-$N$46)/($N$43-$J$43)) -> 0.99775625 | L46: =K46-(($J$46-$N$46)/($N$43-$J$43)) -> 0.8918375 | M46: =L46-(($J$46-$N$46)/($N$43-$J$43)) -> 0.78591875 | N46: =K17 -> 0.68
B47: Base | J47: =Q16 -> 0.655 | K47: =J47-(($J$47-$N$47)/($N$43-$J$43)) -> 0.6525 | L47: =K47-(($J$47-$N$47)/($N$43-$J$43)) -> 0.65 | M47: =L47-(($J$47-$N$47)/($N$43-$J$43)) -> 0.6475 | N47: =Q17 -> 0.645
B48: Optimistic | J48: =J47*(1+W16) -> 1.08075 | K48: =J48-(($J$48-$N$48)/($N$43-$J$43)) -> 0.9705625 | L48: =K48-(($J$48-$N$48)/($N$43-$J$43)) -> 0.860375 | M48: =L48-(($J$48-$N$48)/($N$43-$J$43)) -> 0.7501875 | N48: =W17 -> 0.64
B50: R&D Ex | E50: ='Income - As Reported'!C13 -> 117.7637 | F50: ='Income - As Reported'!D13 -> 133.3088 | G50: ='Income - As Reported'!E13 -> 154.3597 | H50: ='Income - As Reported'!F13 -> 181.4752 | I50: ='Income - As Reported'!G13 -> 203.2598 | J50: =J51*J$36 -> 229.56609 | K50: =K51*K$36 -> 240.86718 | L50: =L51*L$36 -> 252.03631 | M50: =M51*M$36 -> 263.00364 | N50: =N51*N$36 -> 270.60899
B51: % margin | E51: =E50/E$36 -> 0.068025501 | F51: =F50/F$36 -> 0.069469368 | G51: =G50/G$36 -> 0.067135827 | H51: =H50/H$36 -> 0.078448138 | I51: =I50/I$36 -> 0.080204509 | J51: =OFFSET(J51,$E$17,0) -> 0.08688 | K51: =OFFSET(K51,$E$17,0) -> 0.08766 | L51: =OFFSET(L51,$E$17,0) -> 0.08844 | M51: =OFFSET(M51,$E$17,0) -> 0.08922 | N51: =OFFSET(N51,$E$17,0) -> 0.09
B52: Conservative | J52: =J53*(1+K18) -> 0.08688 | K52: =J52-(($J$52-$N$52)/($N$43-$J$43)) -> 0.08766 | L52: =K52-(($J$52-$N$52)/($N$43-$J$43)) -> 0.08844 | M52: =L52-(($J$52-$N$52)/($N$43-$J$43)) -> 0.08922 | N52: =K19 -> 0.09
B53: Base | J53: =$Q$18 -> 0.08 | K53: =J53-(($J$53-$N$53)/($N$43-$J$43)) -> 0.08 | L53: =K53-(($J$53-$N$53)/($N$43-$J$43)) -> 0.08 | M53: =L53-(($J$53-$N$53)/($N$43-$J$43)) -> 0.08 | N53: =Q19 -> 0.08
B54: Optimistic | J54: =J53*(1+W18) -> 0.08624 | K54: =J54-(($J$54-$N$54)/($N$43-$J$43)) -> 0.08343 | L54: =K54-(($J$54-$N$54)/($N$43-$J$43)) -> 0.08062 | M54: =L54-(($J$54-$N$54)/($N$43-$J$43)) -> 0.07781 | N54: =W19 -> 0.075
B56: SG&A | E56: ='Income - As Reported'!C14 -> 92.1622 | F56: ='Income - As Reported'!D14 -> 106.4993 | G56: ='Income - As Reported'!E14 -> 112.5393 | H56: ='Income - As Reported'!F14 -> 121.0237 | I56: ='Income - As Reported'!G14 -> 177.8687 | J56: =J57*J$36 -> 217.68615 | K56: =K57*K$36 -> 221.29775 | L56: =L57*L$36 -> 224.25646 | M56: =M57*M$36 -> 226.52743 | N56: =N57*N$36 -> 225.50749
B57: % margin | E57: =E56/E$36 -> 0.053236947 | F57: =F56/F$36 -> 0.055498505 | G57: =G56/G$36 -> 0.048946836 | H57: =H56/H$36 -> 0.052316151 | I57: =I56/I$36 -> 0.070185407 | J57: =OFFSET(J57,$E$18,0) -> 0.082384 | K57: =OFFSET(K57,$E$18,0) -> 0.080538 | L57: =OFFSET(L57,$E$18,0) -> 0.078692 | M57: =OFFSET(M57,$E$18,0) -> 0.076846 | N57: =OFFSET(N57,$E$18,0) -> 0.075
B58: Conservative | J58: =J59*(1+K20) -> 0.082384 | K58: =J58-(($J$58-$N$58)/($N$43-$J$43)) -> 0.080538 | L58: =K58-(($J$58-$N$58)/($N$43-$J$43)) -> 0.078692 | M58: =L58-(($J$58-$N$58)/($N$43-$J$43)) -> 0.076846 | N58: =K21 -> 0.075
B59: Base | J59: =Q20 -> 0.076 | K59: =J59-(($J$59-$N$59)/($N$43-$J$43)) -> 0.07325 | L59: =K59-(($J$59-$N$59)/($N$43-$J$43)) -> 0.0705 | M59: =L59-(($J$59-$N$59)/($N$43-$J$43)) -> 0.06775 | N59: =Q21 -> 0.065
B60: Optimistic | J60: =J59*(1+W20) -> 0.081624 | K60: =J60-(($J$60-$N$60)/($N$43-$J$43)) -> 0.074968 | L60: =K60-(($J$60-$N$60)/($N$43-$J$43)) -> 0.068312 | M60: =L60-(($J$60-$N$60)/($N$43-$J$43)) -> 0.061656 | N60: =W21 -> 0.055
B63: Total Costs * OpEx | E63: =SUM(E44,E50,E56) -> 1321.388 | F63: =SUM(F44,F50,F56) -> 1548.952 | G63: =SUM(G44,G50,G56) -> 1803.484 | H63: =SUM(H44,H50,H56) -> 1844.723 | I63: =SUM(I44,I50,I56) -> 2048.6885 | J63: =SUM(J44,J50,J56) -> 3363.5317 | K63: =SUM(K44,K50,K56) -> 3203.743 | L63: =SUM(L44,L50,L56) -> 3017.8513 | ... N63: =SUM(N44,N50,N56) -> 2540.7177
B64: % margin | E64: =E63/E36 -> 0.76329192 | F64: =F63/F36 -> 0.8071839 | G64: =G63/G36 -> 0.78439119 | H64: =H63/H36 -> 0.79743725 | I64: =I63/I36 -> 0.80839425 | J64: =J63/J36 -> 1.272939 | K64: =K63/K36 -> 1.1659543 | L64: =L63/L36 -> 1.0589695 | ... N64: =N63/N36 -> 0.845
B66: EBIT | E66: =E36-E63 -> 409.7819 | F66: =F36-F63 -> 370.006 | G66: =G36-G63 -> 495.731 | H66: =H36-H63 -> 468.5913 | I66: =I36-I63 -> 485.5805 | J66: =J36-J63 -> -721.19635 | K66: =K36-K63 -> -455.99968 | L66: =L36-L63 -> -168.05128 | ... N66: =N36-N63 -> 466.04882
B67: % margin | E67: =E66/E36 -> 0.23670808 | F67: =F66/F36 -> 0.1928161 | G67: =G66/G36 -> 0.21560881 | H67: =H66/H36 -> 0.20256275 | I67: =I66/I36 -> 0.19160575 | J67: =J66/J36 -> -0.272939 | K67: =K66/K36 -> -0.16595425 | L67: =L66/L36 -> -0.0589695 | ... N67: =N66/N36 -> 0.155
B69: Taxes | E69: 2021 | F69: =E69+1 -> 2022 | G69: =F69+1 -> 2023 | H69: =G69+1 -> 2024 | I69: =H69+1 -> 2025 | J69: =I69+1 -> 2026 | K69: =J69+1 -> 2027 | L69: =K69+1 -> 2028 | M69: =L69+1 -> 2029 | N69: =M69+1 -> 2030
B70: Earnings Before Taxes | E70: ='Income - As Reported'!C22 -> 416.3517 | F70: ='Income - As Reported'!D22 -> 369.7231 | G70: ='Income - As Reported'!E22 -> 504.9812 | H70: ='Income - As Reported'!F22 -> 472.2137 | I70: ='Income - As Reported'!G22 -> 461.0624
B71: Taxes | E71: ='Income - As Reported'!C53 -> 55.5545 | F71: ='Income - As Reported'!D53 -> 50.9657 | G71: ='Income - As Reported'!E53 -> 76.5779 | H71: ='Income - As Reported'!F53 -> 67.7259 | I71: ='Income - As Reported'!G53 -> 76.3803
B72: % tax rate | E72: =E71/E70 -> 0.13343166 | F72: =F71/F70 -> 0.1378483 | G72: =G71/G70 -> 0.15164505 | H72: =H71/H70 -> 0.14342214 | I72: =I71/I70 -> 0.16566152
B74: Cash Flow Items | E74: 2021 | F74: =E74+1 -> 2022 | G74: =F74+1 -> 2023 | H74: =G74+1 -> 2024 | I74: =H74+1 -> 2025 | J74: =I74+1 -> 2026 | K74: =J74+1 -> 2027 | L74: =K74+1 -> 2028 | M74: =L74+1 -> 2029 | N74: =M74+1 -> 2030
A75: x | B75: D&A | E75: ='Cash Flow - As Reported'!C9 -> 99.112 | F75: ='Cash Flow - As Reported'!D9 -> 96.5684 | G75: ='Cash Flow - As Reported'!E9 -> 93.3212 | H75: ='Cash Flow - As Reported'!F9 -> 94.7147 | I75: ='Cash Flow - As Reported'!G9 -> 104.0418
B76: % of sales | E76: =E75/E$36 -> 0.057251458 | F76: =F75/F$36 -> 0.050323353 | G76: =G75/G$36 -> 0.040588288 | H76: =H75/H$36 -> 0.040943291 | I76: =I75/I$36 -> 0.041053969
A77: x
B78: CapEx | E78: =-'Cash Flow - As Reported'!C23 -> 68.835 | F78: =-'Cash Flow - As Reported'!D23 -> 146.4331 | G78: =-'Cash Flow - As Reported'!E23 -> 183.6785 | H78: =-'Cash Flow - As Reported'!F23 -> 144.669 | I78: =-'Cash Flow - As Reported'!G23 -> 129.0888
B79: % of sales | E79: =E78/E$36 -> 0.039762128 | F79: =F78/F$36 -> 0.076308653 | G79: =G78/G$36 -> 0.079887483 | H79: =H78/H$36 -> 0.062537546 | I79: =I78/I$36 -> 0.050937292
B81: Change in NWC | E81: =-SUM('Cash Flow - As Reported'!C13:C17) -> 82.1388 | F81: =-SUM('Cash Flow - As Reported'!D13:D17) -> 91.2465 | G81: =-SUM('Cash Flow - As Reported'!E13:E17) -> 12.0097 | H81: =-SUM('Cash Flow - As Reported'!F13:F17) -> 40.3929 | I81: =-SUM('Cash Flow - As Reported'!G13:G17) -> -54.4554
A82: x | B82: % of sales | E82: =E81/E$36 -> 0.047446989 | F82: =F81/F$36 -> 0.047550025 | G82: =G81/G$36 -> 0.0052233915 | H82: =H81/H$36 -> 0.017461051 | I82: =I81/I$36 -> -0.021487616
B83: % of change in sales | F83: =F81/(F36-E36) -> 0.4859014 | G83: =G81/(G36-F36) -> 0.031583114 | H83: =H81/(H36-G36) -> 2.8648869 | I83: =I81/(I36-H36) -> -0.24645504
B85: DCF | E85: 2021 | F85: =E85+1 -> 2022 | G85: =F85+1 -> 2023 | H85: =G85+1 -> 2024 | I85: =H85+1 -> 2025 | J85: =I85+1 -> 2026 | K85: =J85+1 -> 2027 | L85: =K85+1 -> 2028 | M85: =L85+1 -> 2029 | N85: =M85+1 -> 2030
B86: Revenue | E86: =E36 -> 1731.1699 | F86: =F36 -> 1918.958 | G86: =G36 -> 2299.215 | H86: =H36 -> 2313.3143 | I86: =I36 -> 2534.269 | J86: =J36 -> 2642.3353 | K86: =K36 -> 2747.7433 | L86: =L36 -> 2849.8 | ... N86: =N36 -> 3006.7666
B87: % growth | E87: =E37 -> -- | F87: =F37 -> 0.10847468 | G87: =G37 -> 0.19815806 | H87: =H37 -> 0.0061322234 | I87: =I37 -> 0.095514345 | J87: =J37 -> 0.042642 | K87: =K37 -> 0.039892 | L87: =L37 -> 0.037142 | ... N87: =N37 -> 0.02
B89: EBIT | E89: =E66 -> 409.7819 | F89: =F66 -> 370.006 | G89: =G66 -> 495.731 | H89: =H66 -> 468.5913 | I89: =I66 -> 485.5805 | J89: =J66 -> -721.19635 | K89: =K66 -> -455.99968 | L89: =L66 -> -168.05128 | ... N89: =N66 -> 466.04882
B90: % margin | E90: =E67 -> 0.23670808 | F90: =F67 -> 0.1928161 | G90: =G67 -> 0.21560881 | H90: =H67 -> 0.20256275 | I90: =I67 -> 0.19160575 | J90: =J67 -> -0.272939 | K90: =K67 -> -0.16595425 | L90: =L67 -> -0.0589695 | ... N90: =N67 -> 0.155
B92: Taxes | E92: =E71 -> 55.5545 | F92: =F71 -> 50.9657 | G92: =G71 -> 76.5779 | H92: =H71 -> 67.7259 | I92: =I71 -> 76.3803 | J92: =J89*J93 -> -151.45123 | K92: =K89*K93 -> -95.759934 | L92: =L89*L93 -> -35.290769 | M92: =M89*M93 -> 29.723369 | N92: =N89*N93 -> 97.870251
A93: x | B93: % tax rate | E93: =E72 -> 0.13343166 | F93: =F72 -> 0.1378483 | G93: =G72 -> 0.15164505 | H93: =H72 -> 0.14342214 | I93: =I72 -> 0.16566152 | J93: =$E$28 -> 0.21 | K93: =$E$28 -> 0.21 | L93: =$E$28 -> 0.21 | M93: =$E$28 -> 0.21 | N93: =$E$28 -> 0.21
B95: EBIAT | E95: =E89-E92 -> 354.2274 | F95: =F89-F92 -> 319.0403 | G95: =G89-G92 -> 419.1531 | H95: =H89-H92 -> 400.8654 | I95: =I89-I92 -> 409.2002 | J95: =J89-J92 -> -569.74512 | K95: =K89-K92 -> -360.23975 | L95: =L89-L92 -> -132.76051 | ... N95: =N89-N92 -> 368.17856
B97: D&A | E97: =E75 -> 99.112 | F97: =F75 -> 96.5684 | G97: =G75 -> 93.3212 | H97: =H75 -> 94.7147 | I97: =I75 -> 104.0418 | J97: =J$86*J98 -> 107.97071 | K97: =K$86*K98 -> 112.27787 | L97: =L$86*L98 -> 116.4481 | M97: =M$86*M98 -> 120.45298 | N97: =N$86*N98 -> 122.86204
B98: % of sales | E98: =E97/E$36 -> 0.057251458 | F98: =F97/F$36 -> 0.050323353 | G98: =G97/G$36 -> 0.040588288 | H98: =H97/H$36 -> 0.040943291 | I98: =I97/I$36 -> 0.041053969 | J98: =$E$29 -> 0.040861849 | K98: =$E$29 -> 0.040861849 | L98: =$E$29 -> 0.040861849 | M98: =$E$29 -> 0.040861849 | N98: =$E$29 -> 0.040861849
B100: CapEx | E100: =E78 -> 68.835 | F100: =F78 -> 146.4331 | G100: =G78 -> 183.6785 | H100: =H78 -> 144.669 | I100: =I78 -> 129.0888 | J100: =J$86*J101 -> 170.30936 | K100: =K$86*K101 -> 177.10334 | L100: =L$86*L101 -> 183.68132 | M100: =M$86*M101 -> 189.99848 | N100: =N$86*N101 -> 193.79845
B101: % of sales | E101: =E100/E$36 -> 0.039762128 | F101: =F100/F$36 -> 0.076308653 | G101: =G100/G$36 -> 0.079887483 | H101: =H100/H$36 -> 0.062537546 | I101: =I100/I$36 -> 0.050937292 | J101: =$E$30 -> 0.064454107 | K101: =$E$30 -> 0.064454107 | L101: =$E$30 -> 0.064454107 | M101: =$E$30 -> 0.064454107 | N101: =$E$30 -> 0.064454107
B103: Change in NWC | E103: =E81 -> 82.1388 | F103: =F81 -> 91.2465 | G103: =G81 -> 12.0097 | H103: =H81 -> 40.3929 | I103: =I81 -> -54.4554 | J103: =J$86*J104 -> 32.201381 | K103: =K$86*K104 -> 33.485959 | L103: =L$86*L104 -> 34.729694 | M103: =M$86*M104 -> 35.924118 | N103: =N$86*N104 -> 36.6426
B104: % of sales | E104: =E103/E$36 -> 0.047446989 | F104: =F103/F$36 -> 0.047550025 | G104: =G103/G$36 -> 0.0052233915 | H104: =H103/H$36 -> 0.017461051 | I104: =I103/I$36 -> -0.021487616 | J104: =$E$31 -> 0.012186713 | K104: =$E$31 -> 0.012186713 | L104: =$E$31 -> 0.012186713 | M104: =$E$31 -> 0.012186713 | N104: =$E$31 -> 0.012186713
B106: Unlevered Free Cash Flow | J106: =(J95+J97-J100-J103)*(YEARFRAC($C$4,$C$5)) -> -404.1068 | K106: =(K95+K97-K100-K103)*(YEARFRAC($C$4,$C$5)) -> -278.95197 | L106: =(L95+L97-L100-L103)*(YEARFRAC($C$4,$C$5)) -> -142.79008 | M106: =(M95+M97-M100-M103)*(YEARFRAC($C$4,$C$5)) -> 3.8610074 | N106: =(N95+N97-N100-N103)*(YEARFRAC($C$4,$C$5)) -> 158.53139
B107: Present Value of Free Cash Flow | J107: =J106/(1+$E$32)^J110 -> -392.01872 | K107: =K106/(1+$E$32)^K110 -> -249.72934 | L107: =L106/(1+$E$32)^L110 -> -115.6847 | M107: =M106/(1+$E$32)^M110 -> 2.8308458 | N107: =N106/(1+$E$32)^N110 -> 105.18858
B109: Period | J109: 1 | K109: =+J109+1 -> 2 | L109: =+K109+1 -> 3 | M109: =+L109+1 -> 4 | N109: =+M109+1 -> 5
B110: Discount Period | J110: =YEARFRAC(C4,C5)/2 -> 0.30416667 | K110: =YEARFRAC(C4,C5)+0.5 -> 1.1083333 | L110: =K110+1 -> 2.1083333 | M110: =L110+1 -> 3.1083333 | N110: =M110+1 -> 4.1083333
B112: Terminal Value | N112: =(N106*(1+E33))/(E32-E33) -> 1902.3767
B113: Present Value of Terminal Value | N113: =N112/(1+E32)^N110 -> 1262.2629
B114: Enterprise Value | N114: =SUM(N113,J107:N107) -> 612.84961
B115: (+) Cash | N115: ='Bal Sheet - As Reported'!G8+'Bal Sheet - As Reported'!G14 -> 151.0323
B116: (-) Debt | N116: 3.8
B117: Implied Equity Value | N117: =N114+N115-N116 -> 760.08191
B118: Share Count | N118: =215402363/1000000 -> 215.40236
B119: Implied Share Price | N119: =N117/N118 -> 3.528661
A127: x

Sheet Income - As Reported
A2: Gentex Corp (GNTX US) - As Reported
A4: In Millions of USD except Per Share | C4: FY 2021 | D4: FY 2022 | E4: FY 2023 | F4: FY 2024 | G4: FY 2025
A5: 12 Months Ending | C5: 12/31/2021 | D5: 12/31/2022 | E5: 12/31/2023 | F5: 12/31/2024 | G5: 12/31/2025
A6: Income Statement
A7: Revenues
A8: Revenues | B8: ARD_REVENUES | C8: 1731.1699 | D8: 1918.958 | E8: 2299.215 | F8: 2313.3143 | G8: 2534.269
A9: Total Revenue | B9: ARD_TOTAL_REVENUES | C9: 1731.1699 | D9: 1918.958 | E9: 2299.215 | F9: 2313.3143 | G9: 2534.269
A10: Operating Expenses
A11: Total Operating Expenses | B11: ARD_TOTAL_OPERATING_EXPENSES | C11: 209.9259 | D11: 239.8081 | E11: 266.899 | F11: 311.3636 | G11: 392.7732
A12: Cost of Goods Sold | B12: ARD_COST_OF_GOODS_SOLD | C12: 1111.4621 | D12: 1309.1439 | E12: 1536.585 | F12: 1542.2241 | G12: 1667.56
A13: R & D Expenditures | B13: ARD_R&D_EXPENDITURES | C13: 117.7637 | D13: 133.3088 | E13: 154.3597 | F13: 181.4752 | G13: 203.2598
A14: Selling General and Administrative Expenses | B14: ARD_SELLING_GENERAL_ADMIN_EXP | C14: 92.1622 | D14: 106.4993 | E14: 112.5393 | F14: 121.0237 | G14: 177.8687
A15: Other Operating Expenses | B15: ARD_OTHER_OPERATING_EXPENSES | C15: — | D15: — | E15: — | F15: — | G15: 11.6447
A16: Write-Down/Impairment of Assets | B16: ARD_WRITEDOWN_IMPAIR_OF_ASSETS | C16: — | D16: — | E16: — | F16: 8.8647 | G16: 0
A17: Gross Profit | B17: ARD_GROSS_PROFITS | C17: 619.7078 | D17: 609.8142 | E17: 762.63 | F17: 771.0902 | G17: 866.7089
A18: Operating Income | B18: ARD_OPERATING_INCOME | C18: 409.782 | D18: 370.0061 | E18: 495.7311 | F18: 459.7266 | G18: 473.9358
A19: Non-Operating Expenses
A20: Income Tax Expense (Benefit) | B20: ARD_INCOME_TAX_EXP_BENEFIT | C20: 55.5545 | D20: 50.9657 | E20: 76.5779 | F20: 67.7259 | G20: 76.3803
A21: Investment Income | B21: ARD_INVESTMENT_INCOME | C21: -3.5898 | D21: -4.7958 | E21: -13.4984 | F21: -13.4028 | G21: 1.2893
A22: Income Before Income Taxes | B22: ARD_INCOME_BEFORE_INCOME_TAXES | C22: 416.3517 | D22: 369.7231 | E22: 504.9812 | F22: 472.2137 | G22: 461.0624
A23: Other Non-Operating (Income)/Expense - Net | B23: ARD_OTH_NON_OPER_INC_EXP_NET | C23: -2.98 | D23: 5.0789 | E23: 4.2482 | F23: 0.9157 | G23: 11.5841
A24: Earnings
A25: Minority/Non Controlling Interest | B25: ARD_MINORITY_NONCONTROL_INTEREST | C25: — | D25: — | E25: — | F25: — | G25: -0.1593
A26: Dividends Per Share | B26: ARD_DVD_PER_SH | C26: 0.48 | D26: 0.48 | E26: 0.48 | F26: 0.48 | G26: 0.48
A27: Basic EPS | B27: ARD_BASIC_EPS | C27: 1.51 | D27: 1.36 | E27: 1.84 | F27: 1.77 | G27: —
A28: Weighted Avg. Shares - Basic | B28: ARD_WEIGHTED_AVG_SHARES_BASIC | C28: — | D28: — | E28: — | F28: — | G28: —
A29: Diluted EPS | B29: ARD_DILUTED_EPS | C29: 1.5 | D29: 1.36 | E29: 1.84 | F29: 1.76 | G29: —
A30: Weighted Avg. Shares - Diluted | B30: ARD_WEIGHTED_AVG_SHARE_DILUTED | C30: — | D30: — | E30: — | F30: — | G30: —
A31: Net Income Available For Common Shareholders | B31: ARD_NET_INC_AVAIL_COM_SHRHLDR | C31: 360.7972 | D31: 318.7574 | E31: 428.4033 | F31: 404.4877 | G31: 384.8414
A32: Profit After Taxation Before Minority | B32: ARD_PROF_AFTER_TAX_BEF_MINORITY | C32: 360.7972 | D32: 318.7574 | E32: 428.4033 | F32: 404.4877 | G32: 384.6821
A33: Cumulative Net Income | B33: ARD_CUMULATIVE_NET_INCOME | C33: 360.7972 | D33: 318.7574 | E33: 428.4033 | F33: 404.4877 | G33: 384.8414
A34: Net Income | B34: ARD_NET_INC | C34: 360.7972 | D34: 318.7574 | E34: 428.4033 | F34: 404.4877 | G34: 384.8414
A35: Comprehensive Income
A36: Foreign Currency Translation Adjustments | B36: ARD_FOR_CRNCY_TRANSLATION_ADJ | C36: — | D36: -4.9528 | E36: -0.5025 | F36: -1.283 | G36: 5.5074
A37: Unrealized Gain (Loss) On Securities | B37: ARD_UNREALIZED_GL_ON_SECS | C37: — | D37: -14.0726 | E37: 10.2383 | F37: 1.8111 | G37: 2.454
A38: Income Tax Exp Related to Comprehensive Income | B38: ARD_INC_TAX_RELATE_TO_COMP_INC | C38: — | D38: 2.9552 | E38: -2.1501 | F38: -0.3803 | G38: -0.3109
A39: Other Comprehensive Income | B39: ARD_OTHER_COMPREHENSIVE_INCOME | C39: — | D39: — | E39: — | F39: — | G39: -0.9734
A40: Total Comprehensive Income | B40: ARD_TOTAL_COMPREHENSIVE_INCOME | C40: — | D40: 302.6872 | E40: 435.9891 | F40: 404.6355 | G40: 391.5185
A41: Net Income - Comprehensive Income | B41: ARD_COMPREHENSIVE_INCOME_NET_INC | C41: — | D41: 318.7574 | E41: 428.4033 | F41: 404.4877 | G41: 384.6821
A42: Net Income - Comprehensive Income | B42: ARDR_COMPR_INCOME_NET_INC | C42: 360.7972 | D42: 318.7574 | E42: 428.4033 | F42: 404.4877 | G42: 384.6821
A43: Others
A44: Reference Items
A45: Amortization Expense | B45: ARDR_AMORT_EXP | C45: 22.2 | D45: 21.7 | E45: 19.7 | F45: 17.9 | G45: 15.3
A46: Depreciation Expense | B46: ARDR_DEPRECIATION_EXP | C46: 76.8 | D46: 74.9 | E46: 73.6 | F46: 76.8 | G46: 88.8
A47: Selling General and Administrative Expense | B47: ARDR_SELLING_GENERAL_ADMIN_EXP | C47: 92.1622 | D47: 106.4993 | E47: 112.5393 | F47: 121.0237 | G47: 177.8687
A48: Depreciation and Amortization | B48: ARDR_DEPRECIATION_AMORTIZATION | C48: 99.112 | D48: 96.5684 | E48: 93.3212 | F48: 94.7147 | G48: 104.0418
A49: Interest Expense | B49: ARDR_INT_EXP | C49: — | D49: — | E49: — | F49: — | G49: —
A50: (Gain)/Loss On Sale of Assets | B50: ARDR_GL_ON_SALE_OF_ASSETS | C50: -0.2578 | D50: — | E50: 0.0878 | F50: -1.2047 | G50: -2.8881
A51: Write-Down/Impairment of Assets | B51: ARDR_WRITEDOWN_IMPAIR_OF_ASSETS | C51: — | D51: — | E51: — | F51: 8.8647 | G51: 0
A52: Restructuring Charges | B52: ARDR_RESTRUCTURING_CHARGES | C52: — | D52: — | E52: — | F52: — | G52: —
A53: Income Tax Expense (Benefit) | B53: ARDR_INCOME_TAX_EXP_BENEFIT | C53: 55.5545 | D53: 50.9657 | E53: 76.5779 | F53: 67.7259 | G53: 76.3803
A54: Foreign Currency Translation Adjustments | B54: ARDR_FOR_CRNCY_TRANSLATION_ADJ | C54: 0.1515 | D54: -4.9528 | E54: -0.5025 | F54: -1.283 | G54: 5.5074
A55: Unrealized Gain (Loss) On Securities | B55: ARDR_UNREALIZED_GL_ON_SECS | C55: -6.4245 | D55: -14.0726 | E55: 10.2383 | F55: 1.8111 | G55: 2.454
A56: Change In Fair Value of Derivatives | B56: ARDR_CHG_FAIR_VAL_OF_DERIVATIVES | C56: — | D56: — | E56: — | F56: — | G56: —
A57: Inc Tax Exp Related to Comprehensive Inc | B57: ARDR_INC_TAX_RELATE_TO_COMP_INC | C57: 1.3491 | D57: 2.9552 | E57: -2.1501 | F57: -0.3803 | G57: -0.3109
A58: Other Comprehensive Income | B58: ARDR_OTHER_COMPREHENSIVE_INCOME | C58: — | D58: — | E58: — | F58: — | G58: -0.9734
A59: Total Cash Common Dividends | B59: ARDR_TOTAL_CASH_COMMON_DVD | C59: 114.4154 | D59: 112.8193 | E59: 111.8244 | F59: — | G59: —
A60: Dividends Per Share | B60: ARDR_DVD_PER_SH | C60: 0.48 | D60: 0.48 | E60: 0.48 | F60: 0.48 | G60: 0.48
A61: Basic EPS | B61: ARDR_BASIC_EPS | C61: 1.51 | D61: 1.36 | E61: 1.84 | F61: 1.77 | G61: —
A62: Weighted Avg. Shares - Basic | B62: ARDR_WEIGHTED_AVG_SHARES_BASIC | C62: — | D62: 230.8253 | E62: 229.4055 | F62: 225.7107 | G62: 217.8342
A63: Diluted EPS | B63: ARDR_DILUTED_EPS | C63: 1.5 | D63: 1.36 | E63: 1.84 | F63: 1.76 | G63: —
A64: Weighted Avg. Shares - Diluted | B64: ARDR_WEIGHTED_AVG_SHARE_DILUTED | C64: — | D64: 231.2195 | E64: 229.7202 | F64: 226.0235 | G64: 217.8487
A65: Stock Based Compensation Expense | B65: ARDR_STK_BASED_COMPENSATION_EXP | C65: 27.4216 | D65: 30.2286 | E65: 39.1974 | F65: 39.5394 | G65: 36.6498
A66: Total Comprehensive Income | B66: ARDR_TOTAL_COMPREHENSIVE_INCOME | C66: 355.8734 | D66: 302.6872 | E66: 435.9891 | F66: 404.6355 | G66: 391.5185
A67: Amortization of Intangible Assets | B67: ARDR_AMORT_OF_INTANGIBLE_ASSETS | C67: — | D67: 21.7 | E67: 19.7 | F67: 17.9 | G67: 15.3
A68: (Gain)/Loss On Sale of Investments | B68: ARDR_GL_ON_SALE_OF_INVESTMENTS | C68: -1.072 | D68: — | E68: 5.9847 | F68: 4.6257 | G68: 4.44
A69: Current Income Tax Expense (Benefit) | B69: ARDR_CUR_INCOME_TAX_EXP_BENEFIT | C69: 97.2493 | D69: 68.7435 | E69: 94.313 | F69: 80.1474 | G69: 94.7866
A70: Net Inc Available For Common Shareholders | B70: ARDR_NET_INC_AVAIL_COM_SHRHLDR | C70: — | D70: 318.7574 | E70: 428.4033 | F70: 404.4877 | G70: 384.8414
A71: Effective Tax Rate - % | B71: ARDR_EFFECTIVE_TAX_RATE_PCT | C71: 13.3 | D71: 13.8 | E71: 15.2 | F71: 14.3 | G71: 16.6
A72: Total Fees Paid To Audit Firms | B72: ARDR_TOT_FEES_PAID_AUDIT_FIRMS | C72: 0.6789 | D72: 0.6325 | E72: 0.7319 | F72: 0.7909 | G72: —
A73: Auditor Expense - Audit | B73: ARDR_AUDITOR_EXP_AUDIT | C73: 0.545 | D73: 0.6325 | E73: 0.7319 | F73: 0.7909 | G73: —
A74: Auditor Expense - Non Audit | B74: ARDR_AUDITOR_EXP_NON_AUDIT | C74: 0.1339 | D74: 0 | E74: 0 | F74: 0 | G74: —
A75: Diluted Net Income | B75: ARDR_DILUTED_NET_INCOME | C75: — | D75: — | E75: — | F75: — | G75: 384.8414
A76: Statutory Tax Rate - % | B76: ARDR_STATUTORY_TAX_RATE_PCT | C76: 21 | D76: 21 | E76: 21 | F76: 21 | G76: 21
A77: ARDR Restructuring After Tax | B77: ARDR_RESTRUCTURING_AFTER_TAX | C77: — | D77: — | E77: — | F77: — | G77: —
A78: Advertising Expenses | B78: ARDR_ADVERTISING_EXPENSES | C78: — | D78: — | E78: — | F78: — | G78: —
A79: Income Tax Exp - Current Taxes (Intl) | B79: ARDR_ITE_CURRENT_TAX_INTL | C79: 2.0984 | D79: 1.7617 | E79: 2.0915 | F79: 1.931 | G79: 2.3683
A80: Income Tax Exp - Current Taxes (National) | B80: ARDR_ITE_CURRENT_TAX_NATL | C80: 89.5079 | D80: 62.671 | E80: 85.979 | F80: 73.5383 | G80: 86.6325
A81: Income Tax Exp - Current Taxes (Local) | B81: ARDR_ITE_CURRENT_TAX_LCL | C81: 5.6429 | D81: 4.3108 | E81: 6.2425 | F81: 4.678 | G81: 5.7858
A82: Income Tax Exp - Deferred Taxes (National) | B82: ARDR_ITE_DEFERRED_TAX_NATL | C82: -41.6948 | D82: -17.7778 | E82: -17.7351 | F82: -12.4214 | G82: -18.4062
A83: Restructuring/Workflow Bal - Non-GAAP COGS | B83: ARDR_RSTRCT_WF_BAL_NON_GAAP_COGS | C83: — | D83: — | E83: — | F83: — | G83: —
A84: ARDR Gross Margin | B84: ARDR_GROSS_MARGIN | C84: 35.8 | D84: 31.8 | E84: 33.2 | F84: 33.3 | G84: 34.2
A85: ARDR Revenue Growth | B85: ARDR_REVENUE_GROWTH | C85: 3 | D85: 11 | E85: 20 | F85: 1 | G85: 10
A86: Capital Expenditures As Reported | B86: ARDR_CAPEX_AS_REPORTED | C86: — | D86: 146.4331 | E86: 183.6785 | F86: 144.669 | G86: 129.0888
A87: ARDR Stock Based Compensation CF Pre Tax | B87: ARDR_STK_BSD_CMPNSTN_CF_PRE_TAX | C87: 27.4216 | D87: 30.2286 | E87: 39.1974 | F87: 39.5394 | G87: 36.6498
A88: Source: Bloomberg | C88: Right click to show data transparency (not supported for all values)

Sheet Cash Flow - As Reported
A2: Gentex Corp (GNTX US) - As Reported
A4: In Millions of USD except Per Share | C4: FY 2021 | D4: FY 2022 | E4: FY 2023 | F4: FY 2024 | G4: FY 2025
A5: 12 Months Ending | C5: 12/31/2021 | D5: 12/31/2022 | E5: 12/31/2023 | F5: 12/31/2024 | G5: 12/31/2025
A6: Cash Flow
A7: Cash From Operating Activities
A8: Net Income - CF | B8: ARD_NET_INCOME_CF | C8: 360.7972 | D8: 318.7574 | E8: 428.4033 | F8: 404.4877 | G8: 384.6821
A9: Depreciation And Amortization - CF | B9: ARD_DEPRECIATION_AND_AMORT_CF | C9: 99.112 | D9: 96.5684 | E9: 93.3212 | F9: 94.7147 | G9: 104.0418
A10: Deferred Income Taxes - CF | B10: ARD_DEFERRED_INCOME_TAXES_CF | C10: -41.6948 | D10: -17.7778 | E10: -17.7351 | F10: -12.4214 | G10: -18.4062
A11: Disposal/Sale of Assets | B11: ARD_DISPOSAL_SALE_OF_ASSETS | C11: -0.2578 | D11: -0.0423 | E11: 0.0878 | F11: -1.2047 | G11: -2.8881
A12: Stock Based Compensation | B12: ARD_STOCK_BASED_COMPENSATION | C12: 27.4216 | D12: 30.2286 | E12: 39.1974 | F12: 39.5394 | G12: 36.6498
A13: Change in Inventories | B13: ARD_CHANGE_IN_INVENTORIES | C13: -89.9756 | D13: -88.0928 | E13: 2.1272 | F13: -32.6244 | G13: 18.1383
A14: Change in Accounts Payable | B14: ARD_CHANGE_IN_ACCOUNTS_PAYABLE | C14: 7.2663 | D14: 37.4235 | E14: 40.9515 | F14: -26.0212 | G14: 52.4026
A15: Change in Accounts Receivable | B15: ARD_CHG_IN_ACCOUNTS_RECEIVABLE | C15: 35.1354 | D15: -26.6988 | E15: -45.2511 | F15: 27.1067 | G15: -14.6155
A16: Change in Prepaid Expenses | B16: ARD_CHANGE_IN_PREPAID_EXP | C16: -20.242 | D16: -28.7883 | E16: -4.1019 | F16: -9.8736 | G16: 0.2146
A17: Change in Accrued Expenses | B17: ARD_CHANGE_IN_ACCRUED_EXP | C17: -14.3229 | D17: 14.9099 | E17: -5.7354 | F17: 1.0196 | G17: -1.6846
A18: Impairments | B18: ARD_IMPAIRMENTS | C18: — | D18: — | E18: — | F18: 8.8647 | G18: 14.082
A19: Total Cash Flows From Operations | B19: ARD_TOT_CASH_FLOWS_FROM_OPS | C19: 362.1676 | D19: 338.2005 | E19: 537.2496 | F19: 498.2132 | G19: 587.1263
A20: Gain (Loss) On Sale of Investments and Mkt Sec | B20: ARD_GL_ON_SALE_OF_INV_MKT_SEC | C20: -1.072 | D20: 1.7129 | E20: 5.9847 | F20: 4.6257 | G20: 14.5096
A21: Cash From Investing Activities
A22: Disposal of Fixed Assets | B22: ARD_DISPOSAL_OF_FIXED_ASSETS | C22: 2.5779 | D22: 0.3139 | E22: 0.2927 | F22: 3.3106 | G22: 8.4079
A23: Capital Expenditures | B23: ARD_CAPITAL_EXPENDITURES | C23: -68.835 | D23: -146.4331 | E23: -183.6785 | F23: -144.669 | G23: -129.0888
A24: Proceeds From Investments | B24: ARD_PROCEEDS_FROM_INVESTMENTS | C24: 83.9274 | D24: 40.9296 | E24: 76.2923 | F24: 58.91 | G24: 76.913
A25: Purchases of Investments | B25: ARD_PURCHASES_OF_INVESTMENTS | C25: -113.2042 | D25: -30.1074 | E25: -168.933 | F25: -78.7461 | G25: -48.7375
A26: Acquisition of Business | B26: ARD_ACQUISITION_OF_BUSINESS | C26: -12.0715 | D26: 0 | E26: -18.9365 | F26: -2.8708 | G26: -16.2133
A27: Other Investing Activities | B27: ARD_OTHER_INVESTING_ACTIVITIES | C27: -5.5014 | D27: -3.6112 | E27: -4.4534 | F27: -38.0132 | G27: -158.1809
A28: Purchase Of Associates/Joint Ventures | B28: ARD_PURCHASE_ASSOC_JOINT_VENTURE | C28: — | D28: -33.8303 | E28: — | F28: — | G28: —
A29: Total Cash Flows From Investing | B29: ARD_TOT_CASHFLOWS_FROM_INVESTING | C29: -113.107 | D29: -172.7385 | E29: -299.4163 | F29: -202.0784 | G29: -266.8995
A30: Cash from Financing Activities
A31: Dividends Paid | B31: ARD_DIVIDEND_PD | C31: -115.2856 | D31: -113.0919 | E31: -112.1501 | F31: -110.438 | G31: -106.8606
A32: Increase In Long-Term Borrowings | B32: ARD_INCR_IN_LT_BORROW | C32: 0 | D32: — | E32: — | F32: — | G32: —
A33: Decrease In Long-Term Borrowings | B33: ARD_DECR_IN_LT_BORROW | C33: 0 | D33: 0 | E33: — | F33: — | G33: —
A34: Issuance of Common Stock | B34: ARD_ISSUANCE_OF_COMMON_STOCK | C34: 29.8088 | D34: 16.6023 | E34: 29.3983 | F34: 27.2951 | G34: 14.4602
A35: Repurchase of Common Stock | B35: ARD_REPURCHASE_OF_COMMON_STOCK | C35: -324.6431 | D35: -112.5294 | E35: -147.4011 | F35: -206.1081 | G35: -315.4995
A36: Net Change In Cash | B36: ARD_NET_CHANGE_IN_CASH | C36: -161.0594 | D36: -43.557 | E36: 7.6804 | F36: 6.8837 | G36: -87.6731
A37: Cash and Cash Equivalents (End of Period) | B37: ARD_CASH_CASH_EQUIV_END_OF_PER | C37: 262.3117 | D37: 218.7546 | E37: 226.435 | F37: 233.3188 | G37: 145.6457
A38: Cash and Cash Equivalents (Beg of Period) | B38: ARD_CASH_CASH_EQUIV_BEG_OF_PER | C38: 423.371 | D38: 262.3117 | E38: 218.7546 | F38: 226.435 | G38: 233.3188
A39: Total Cash Flows From Financing | B39: ARD_TOT_CASHFLOWS_FROM_FINANCING | C39: -410.12 | D39: -209.0191 | E39: -230.1529 | F39: -289.2511 | G39: -407.8998
A40: Reference Items
A41: Cash Paid For Taxes | B41: ARDR_CASH_PAID_FOR_TAXES | C41: — | D41: — | E41: — | F41: — | G41: —
A42: Source: Bloomberg | C42: Right click to show data transparency (not supported for all values)

Sheet Bal Sheet - As Reported
A2: Gentex Corp (GNTX US) - As Reported
A4: In Millions of USD except Per Share | C4: FY 2021 | D4: FY 2022 | E4: FY 2023 | F4: FY 2024 | G4: FY 2025
A5: 12 Months Ending | C5: 12/31/2021 | D5: 12/31/2022 | E5: 12/31/2023 | F5: 12/31/2024 | G5: 12/31/2025
A6: Balance Sheet
A7: Current Assets
A8: Cash and Equivalents | B8: ARD_CASH_AND_EQUIVALENTS | C8: 262.3117 | D8: 214.7546 | E8: 226.435 | F8: 233.3188 | G8: 145.6457
A9: Accounts Receivable - Trade | B9: ARD_ACCTS_RECEIVABLE_TRADE | C9: 249.7949 | D9: 276.4938 | E9: 321.8099 | F9: 295.3444 | G9: 368.5176
A10: Inventories | B10: ARD_INVENTORY | C10: 316.2674 | D10: 404.3603 | E10: 402.473 | F10: 436.4974 | G10: 516.2536
A11: Prepaid Expenses and Other | B11: ARD_PREPAID_EXP_AND_OTHER | C11: — | D11: — | E11: — | F11: — | G11: —
A12: Restricted Cash (Short-Term) | B12: ARD_RESTRICTED_CASH_ST | C12: — | D12: 4 | E12: 0 | F12: — | G12: —
A13: Other Current Assets | B13: ARD_OTHER_CURRENT_ASSETS | C13: 39.1781 | D13: 26.0363 | E13: 32.6638 | F13: 49.8628 | G13: 92.631
A14: Short-Term Investments | B14: ARD_ST_INVEST | C14: 5.4236 | D14: 23.0074 | E14: 14.3565 | F14: 22.3048 | G14: 5.3866
A15: Total Current Assets | B15: ARD_TOTAL_CUR_ASSETS | C15: 872.9757 | D15: 948.6524 | E15: 997.7382 | F15: 1037.3282 | G15: 1128.4345
A16: Noncurrent Assets
A17: Long Term Investments | B17: ARD_LT_INVEST | C17: 207.6931 | D17: 153.906 | E17: 299.0809 | F17: 339.604 | G17: 272.9759
A18: Land and Buildings | B18: ARD_LAND_AND_BUILDINGS | C18: 363.6464 | D18: 376.9344 | E18: 472.1123 | F18: 531.2611 | G18: 591.488
A19: Construction In Progress | B19: ARD_CONSTRUCTION_IN_PROGRESS | C19: 77.5922 | D19: 165.5749 | E19: 158.3272 | F19: 177.9073 | G19: 83.0484
A20: Furniture/Machinery/Equipment | B20: ARD_FURNITURE_MACHINERY_EQUIP | C20: 883.2401 | D20: 935.8483 | E20: 1011.9307 | F20: 1065.1097 | G20: 1240.2128
A21: Property Plant & Equipment - Gross | B21: ARD_PROPERTY_PLANT_EQUIP_GROSS | C21: 1324.4786 | D21: 1478.3575 | E21: 1642.3703 | F21: 1774.2781 | G21: 1914.7492
A22: Accumulated Depreciation | B22: ARD_ACCUMULATED_DEPREC | C22: 860.357 | D22: 928.3245 | E22: 989.4926 | F22: 1045.7966 | G22: 1123.8138
A23: Property Plant & Equipment - Net | B23: ARD_PROPERTY_PLANT_EQUIP_NET | C23: 464.1217 | D23: 550.033 | E23: 652.8777 | F23: 728.4815 | G23: 790.9354
A24: Deferred Income Tax Asset (Long-Term) | B24: ARD_DEFERRED_INC_TAX_ASSET_LT | C24: — | D24: 25.5287 | E24: 41.1138 | F24: 53.1548 | G24: 108.3386
A25: Other Intangible Assets | B25: ARD_OTHER_INTANGIBLE_ASSET | C25: 272.6404 | D25: 286.8763 | E25: 280.5215 | F25: 195.1572 | G25: 189.3414
A26: Investment In Affiliates/Joint Ventures | B26: ARD_INVESTMENT_IN_AFFILIATE_JV | C26: — | D26: 48.426 | E26: — | F26: — | G26: —
A27: Goodwill | B27: ARD_GOODWLL | C27: 313.9602 | D27: 313.8075 | E27: 340.1056 | F27: 340.6689 | G27: 357.2119
A28: Patents/Trademarks/Copyrights | B28: ARD_PATENTS_TRADEMRK_COPYRIGHT | C28: — | D28: — | E28: — | F28: 66.4264 | G28: 81.3552
A29: Total Non-Current Assets | B29: ARD_TOTAL_NONCURRENT_ASSETS | C29: 1258.4154 | D29: 1378.5775 | E29: 1613.6994 | F29: — | G29: —
A30: Total Assets | B30: ARD_TOT_ASSETS | C30: 2131.3912 | D30: 2327.2299 | E30: 2611.4376 | F30: 2760.821 | G30: 2928.5928
A31: Current Liabilities
A32: Accounts Payable - Trade | B32: ARD_ACCOUNTS_PAYABLE_TRADE | C32: 98.3429 | D32: 151.74 | E32: 184.3988 | F32: 168.3149 | G32: 248.9835
A33: Current Portion of Long-Term Debt | B33: ARD_CURRENT_PORTION_OF_LT_DEBT | C33: — | D33: — | E33: — | F33: — | G33: —
A34: Accrued Compensation/Postretirement Obligation | B34: ARD_ACC_COMP_POSTRETIRE_OBLIG | C34: 14.0196 | D34: 17.5176 | E34: 22.7256 | F34: 19.5264 | G34: 23.1972
A35: Accrued Expenses | B35: ARD_ACCRUED_EXPENSES | C35: 19.1409 | D35: 19.2084 | E35: 20.8989 | F35: 21.0875 | G35: 29.3581
A36: Dividends Accrued/Payable | B36: ARD_DVD_ACCRUED_PAYABLE | C36: 28.3729 | D36: 28.1003 | E36: 27.7747 | F36: 27.2649 | G36: 25.8534
A37: Other Current Liabilities | B37: ARD_OTHER_CURRENT_LIABILITIES | C37: 21.5829 | D37: 15.2595 | E37: 15.1175 | F37: 16.0595 | G37: 59.3038
A38: Income Taxes Accrued/Payable | B38: ARD_INCOME_TAX_ACCRUED_PAYABLE | C38: 0.1969 | D38: 18.7269 | E38: 0.6934 | F38: 0.4395 | G38: 0.847
A39: Total Current Liabilities | B39: ARD_TOTAL_CURRENT_LIABILITIES | C39: 181.6561 | D39: 250.5528 | E39: 271.609 | F39: 252.6927 | G39: 387.543
A40: Non Current Liabilities
A41: Long Term Debt | B41: ARD_LT_DEBT | C41: — | D41: — | E41: — | F41: — | G41: —
A42: Deferred Income Taxes (Liabilities) | B42: ARD_DEFERRED_INCOME_TAXES_LIAB | C42: 0 | D42: — | E42: — | F42: — | G42: 0.9089
A43: Other Noncurrent Liabilities | B43: ARD_OTH_NONCURRENT_LIABILITIES | C43: 11.7466 | D43: 10.8844 | E43: 27.3115 | F43: 36.0286 | G43: 49.209
A44: Total Liabilities | B44: ARD_TOT_LIABILITIES | C44: 193.4027 | D44: 261.4371 | E44: 298.9205 | F44: 288.7213 | G44: 437.6609
A45: Stockholder Equity
A46: Preferred Stock | B46: ARD_PREFERRED_STOCK | C46: — | D46: — | E46: — | F46: — | G46: —
A47: Minority/Non Controlling Int (Stckhldrs Eqty) | B47: ARD_MIN_NONCONTROL_INT_SE | C47: — | D47: — | E47: — | F47: 4.149 | G47: 0
A48: Common Stock | B48: ARD_COMMON_STOCK | C48: 14.1865 | D48: 14.0502 | E48: 13.8873 | F48: 13.6324 | G48: 12.9267 | J48: share value (12/31/2025 | K48: 23.27
A49: Additional Paid In Capital | B49: ARD_ADDITIONAL_PAID_IN_CAPITAL | C49: 879.4134 | D49: 917.4993 | E49: 968.2459 | F49: 1010.4404 | G49: 1008.5893 | J49: enterprise value | K49: =(K48*G53)+G47+G77+G94+G34-G14-G8 -> 5171.7927
A50: Accumulated Other Comprehensive Income | B50: ARD_ACC_OTH_COMPREHENSIVE_INC | C50: 1.9272 | D50: -14.1429 | E50: -6.5571 | F50: -6.4093 | G50: 1.0367
A51: Retained Earnings (Accumulated Deficit) | B51: ARD_RETAINED_EARN_ACC_DEFICIT | C51: 1042.4614 | D51: 1148.3863 | E51: 1336.941 | F51: 1450.2871 | G51: 1466.046
A52: Other Equity | B52: ARD_OTHER_EQUITY | C52: — | D52: — | E52: — | F52: — | G52: -0.769
A53: Shares Outstanding | B53: ARD_SHARES_OUTSTANDING | C53: 236.4408 | D53: 236.4408 | E53: 231.4554 | F53: 231.4554 | G53: 227.2075
A54: Par Value | B54: ARD_PAR_VALUE | C54: 0.06 | D54: 0.06 | E54: 0.06 | F54: 0.06 | G54: 0.06
A55: Total Shareholders Equity | B55: ARD_TOTAL_SHAREHOLDERS_EQUITY | C55: 1937.9885 | D55: 2065.7928 | E55: 2312.5171 | F55: 2467.9507 | G55: 2490.9319
A56: Shares Authorized | B56: ARD_SHARES_AUTHORIZED | C56: 400 | D56: 400 | E56: 400 | F56: 400 | G56: 400
A57: Total Liabilities and Shareholders Equity | B57: ARD_TOT_LIAB_AND_SHAREHOLDER_EQY | C57: 2131.3912 | D57: 2327.2299 | E57: 2611.4376 | F57: 2760.821 | G57: 2928.5928
A58: Reference Items
A59: Inventories | B59: ARDR_INVENTORY | C59: 316.2674 | D59: 404.3603 | E59: 402.473 | F59: 436.4974 | G59: 516.2536
A60: Deferred Income Tax Asset (LT) | B60: ARDR_DEFERRED_INC_TAX_ASSET_LT | C60: 77.7493 | D60: 87.6722 | E60: 107.8643 | F60: 126.0274 | G60: 189.9074
A61: Other Intangible Assets | B61: ARDR_OTHER_INTANGIBLE_ASSET | C61: 83.6646 | D61: 68.1359 | E61: 66.0059 | F61: 99.1572 | G61: 189.3414
A62: Goodwill | B62: ARDR_GOODWLL | C62: 313.9602 | D62: 313.8075 | E62: 340.1056 | F62: 340.6689 | G62: 357.2119
A63: Patents/Trademarks/Copyrights | B63: ARDR_PATENTS_TRADEMRK_COPYRIGHT | C63: 85.4508 | D63: 119.5154 | E63: 118.5156 | F63: 66.4264 | G63: 81.3552
A64: Deferred Income Taxes (Liabilities) | B64: ARDR_DEFERRED_INCOME_TAXES_LIAB | C64: 72.9536 | D64: 62.1435 | E64: 66.7506 | F64: 72.8725 | G64: 82.4777
A65: Min/Non Cntrlling Int(Stckhldrs Eqty) | B65: ARDR_MIN_NONCONTROL_INT_SE | C65: — | D65: — | E65: — | F65: 4.149 | G65: 0
A66: Common Stock | B66: ARDR_COMMON_STOCK | C66: 14.1865 | D66: 14.0502 | E66: 13.8873 | F66: 13.6324 | G66: 12.9267
A67: Additional Paid In Capital | B67: ARDR_ADDITIONAL_PAID_IN_CAPITAL | C67: 879.4134 | D67: 917.4993 | E67: 968.2459 | F67: 1010.4404 | G67: 1008.5893
A68: Accumulated Other Comprehensive Income | B68: ARDR_ACC_OTH_COMPREHENSIVE_INC | C68: 1.9272 | D68: -14.1429 | E68: -6.5571 | F68: -6.4093 | G68: 0.2678
A69: Retained Earnings (Accumulated Deficit) | B69: ARDR_RETAINED_EARN_ACC_DEFICIT | C69: 1042.4614 | D69: 1148.3863 | E69: 1336.941 | F69: 1450.2871 | G69: 1466.046
A70: Shares Outstanding | B70: ARDR_SHARES_OUTSTANDING | C70: 236.4408 | D70: 234.1693 | E70: 231.4554 | F70: 227.2075 | G70: 215.445
A71: Par Value | B71: ARDR_PAR_VALUE | C71: 0.06 | D71: 0.06 | E71: 0.06 | F71: 0.06 | G71: 0.06
A72: Raw Materials | B72: ARDR_RAW_MATERIAL | C72: 235.0143 | D72: 304.184 | E72: 283.1266 | F72: 307.0988 | G72: 280.645
A73: Work In Progress | B73: ARDR_WORK_IN_PROGRESS | C73: 34.0322 | D73: 45.5123 | E73: 46.344 | F73: 48.0987 | G73: 64.4734
A74: Finished Goods | B74: ARDR_FINISHED_GOOD | C74: 47.221 | D74: 54.664 | E74: 73.0025 | F74: 81.2999 | G74: 171.1352
A75: Total Line of Credit | B75: ARDR_TOTAL_LINE_OF_CREDIT | C75: 150 | D75: 150 | E75: 250 | F75: 250 | G75: 250
A76: Total Available Line of Credit | B76: ARDR_TOTAL_AVAIL_LINE_OF_CREDIT | C76: 150 | D76: 150 | E76: 250 | F76: 250 | G76: 250
A77: Future Minimum Operating Lease Obligations | B77: ARDR_FUT_MIN_OPER_LEASE_OBLIG | C77: 2.4001 | D77: 2.2002 | E77: 3.7411 | F77: 4.966 | G77: 9.1443
... A81: Rental Expense - Year 4 | B81: ARDR_RENTAL_EXP_YR4 | C81: 0.0074 | D81: 0.0374 | E81: 0.2427 | F81: 0.6813 | G81: 0.7787
A82: Rental Expense - Year 5 | B82: ARDR_RENTAL_EXP_YR5 | C82: — | D82: — | E82: — | F82: — | G82: 0.2157
A83: Rental Expense - Beyond Year 5 | B83: ARDR_RENTAL_EXP_BEYOND_YR5 | C83: 0.0005 | D83: 0.001 | E83: 0.0038 | F83: 0.0816 | G83: 0.0706
A84: Deferred Tax Liabilities (LT) | B84: ARDR_DEFERRED_TAX_LIAB_LT | C84: 72.9536 | D84: — | E84: — | F84: — | G84: —
A85: Deferred Tax Assets (LT) | B85: ARDR_DEFERRED_TAX_ASSETS_LT | C85: 77.7493 | D85: 87.6722 | E85: 107.8643 | F85: 126.0274 | G85: 189.9074
A86: Allowance For Doubtful Accounts | B86: ARDR_ALLOW_FOR_DOUBTFUL_ACCTS | C86: 3.1762 | D86: 2.9671 | E86: 2.9671 | F86: 2.6652 | G86: 2.0369
A87: Total Shareholders Equity | B87: ARDR_TOTAL_SHAREHOLDERS_EQUITY | C87: 1937.9885 | D87: 2065.7928 | E87: 2312.5171 | F87: 2472.0997 | G87: 2487.8297
A88: Number of Employees | B88: ARDR_NUMBER_EMPLOYEES | C88: 4998 | D88: 5466 | E88: 6245 | F88: 6184 | G88: 6398
A89: Shares Outstanding From The Front Cover | B89: ARDR_SHARE_OUT_FROM_FRONT_COVER | C89: 236.4214 | D89: 234.1778 | E89: 231.4919 | F89: 227.1957 | G89: 215.4024
A90: Licenses | B90: ARDR_LICENSES | C90: 96 | D90: 96 | E90: 96 | F90: 96 | G90: —
A91: Customer Lists/Contracts | B91: ARDR_CUSTOMER_LISTS_CONTRACTS | C91: 7.525 | D91: 3.225 | E91: 0 | F91: 0 | G91: 0
A92: Accumulated Amortization Intangible Assets | B92: ARDR_ACCCUM_AMORT_INTANG_ASSET | C92: 159.225 | D92: 178.525 | E92: 196.75 | F92: 213.3388 | G92: 227.2425
A93: Options Granted During Period | B93: ARDR_OPTIONS_GRANTED_DURING_PER | C93: 1.434 | D93: 1.219 | E93: 0.768 | F93: 0.292 | G93: 0.528
A94: Options Outstanding End Period | B94: ARDR_OPTIONS_OUTSTANDING_END_PER | C94: 4.535 | D94: 4.872 | E94: 4.387 | F94: 3.738 | G94: 3.365
A95: Options Exercised During the Period | B95: ARDR_OPTIONS_EXERCISED_DUR_PER | C95: 1.184 | D95: 0.53 | E95: 1.023 | F95: 0.784 | G95: 0.336
A96: Deferred Income Tax Liability Long -Term | B96: ARDR_DEFERRED_INC_TAB_LIAB_LT | C96: 0 | D96: — | E96: — | F96: — | G96: —
A97: Total Credit Utilized | B97: ARDR_TOTAL_CREDIT_UTILIZED | C97: 0 | D97: 0 | E97: — | F97: — | G97: —
A98: Purchase Obligations | B98: ARDR_PURCHASE_OBLIGATIONS | C98: — | D98: — | E98: — | F98: — | G98: —
A99: Number of Common Shares Repurchased | B99: ARDR_COMMON_SHARES_REPURCHASED | C99: 9.5952 | D99: 7.3314 | E99: 3.4853 | F99: 6.4018 | G99: 11.5592
A100: ARDR Total Operating Liabilities | B100: ARDR_TOTAL_OPERATING_LIABILITIES | C100: 2.3825 | D100: 2.1495 | E100: 3.5702 | F100: 4.6828 | G100: 8.7285
A101: Fair Value Assets Recur - Level 1 | B101: ARDR_FV_ASSETS_REC_LEVEL_1 | C101: 267.7736 | D101: 222.1166 | E101: 248.2533 | F101: 283.1736 | G101: 146.5704
A102: Fair Value Assets Recur - Level 2 | B102: ARDR_FV_ASSETS_REC_LEVEL_2 | C102: 190.8374 | D102: 156.4281 | E102: 163.5449 | F102: 156.1534 | G102: 110.8927
A103: Fair Value Assets Recur - Level 3 | B103: ARDR_FV_ASSETS_REC_LEVEL_3 | C103: 0 | D103: 0 | E103: 0 | F103: 0 | G103: 0
A104: Fair Value Assets Recur - Total | B104: ARDR_FV_ASSETS_REC_TOTAL | C104: 458.611 | D104: 378.5448 | E104: 411.7982 | F104: 439.327 | G104: 257.4631
A105: Contractual Obligations - Year 1 | B105: ARDR_CONTRACTUAL_OBLIG_YEAR_1 | C105: 3.5262 | D105: 16.8073 | E105: 9.9533 | F105: 14.9436 | G105: 2.7473
...
